p8xxpy/__init__.py
p8xxpy/styles.py
p8xxpy-0.1.dist-info/METADATA
p8xxpy-0.1.dist-info/WHEEL
p8xxpy-0.1.dist-info/top_level.txt
p8xxpy-0.1.dist-info/RECORD
