Metadata-Version: 2.1
Name: p8xxpy
Version: 0.1
Summary: Uma biblioteca para estilizar interfaces gráficas em Python, tornando-as mais bonitas e atraentes
Home-page: https://github.com/seunome/p8xxpy
Author: bruno
Author-email: miguel100eduardoluiz@gmail.com
Classifier: Programming Language :: Python :: 3
Classifier: License :: OSI Approved :: MIT License
Classifier: Operating System :: OS Independent
Classifier: Development Status :: 3 - Alpha
Classifier: Intended Audience :: Developers
Classifier: Topic :: Software Development :: Libraries :: Application Frameworks
Classifier: Topic :: Software Development :: User Interfaces
Requires-Python: >=3.6
